foo/__init__.py
graphscope.runtime/lib/bcprov-jdk15on-1.67.jar
graphscope.runtime/lib/conscrypt-openjdk-uber-2.5.1.jar
graphscope.runtime/lib/curator-client-2.12.0.jar
graphscope.runtime/lib/curator-framework-2.12.0.jar
graphscope.runtime/lib/curator-recipes-2.12.0.jar
graphscope.runtime/lib/curator-test-2.12.0.jar
graphscope.runtime/lib/gremlin-core-3.5.1.jar
graphscope.runtime/lib/gremlin-driver-3.5.1.jar
graphscope.runtime/lib/gremlin-groovy-3.5.1.jar
graphscope.runtime/lib/gremlin-server-3.5.1.jar
graphscope.runtime/lib/gremlin-shaded-3.5.1.jar
graphscope.runtime/lib/groovy-2.5.14-indy.jar
graphscope.runtime/lib/groovy-2.5.14.jar
graphscope.runtime/lib/groovy-cli-picocli-2.5.14.jar
graphscope.runtime/lib/groovy-console-2.5.14.jar
graphscope.runtime/lib/groovy-groovysh-2.5.14-indy.jar
graphscope.runtime/lib/groovy-json-2.5.14-indy.jar
graphscope.runtime/lib/groovy-jsr223-2.5.14-indy.jar
graphscope.runtime/lib/groovy-jsr223-2.5.14.jar
graphscope.runtime/lib/groovy-swing-2.5.14.jar
graphscope.runtime/lib/groovy-templates-2.5.14.jar
graphscope.runtime/lib/groovy-xml-2.5.14.jar
graphscope.runtime/lib/grpc-all-1.42.1.jar
graphscope.runtime/lib/grpc-alts-1.42.1.jar
graphscope.runtime/lib/grpc-api-1.42.1.jar
graphscope.runtime/lib/grpc-auth-1.42.1.jar
graphscope.runtime/lib/grpc-context-1.42.1.jar
graphscope.runtime/lib/grpc-core-1.42.1.jar
graphscope.runtime/lib/grpc-grpclb-1.42.1.jar
graphscope.runtime/lib/grpc-netty-1.42.1.jar
graphscope.runtime/lib/grpc-netty-shaded-1.42.1.jar
graphscope.runtime/lib/grpc-okhttp-1.42.1.jar
graphscope.runtime/lib/grpc-protobuf-1.42.1.jar
graphscope.runtime/lib/grpc-protobuf-lite-1.42.1.jar
graphscope.runtime/lib/grpc-rls-1.42.1.jar
graphscope.runtime/lib/grpc-services-1.42.1.jar
graphscope.runtime/lib/grpc-stub-1.42.1.jar
graphscope.runtime/lib/grpc-testing-1.42.1.jar
graphscope.runtime/lib/grpc-xds-1.42.1.jar
graphscope.runtime/lib/hadoop-annotations-3.2.3.jar
graphscope.runtime/lib/hadoop-auth-3.2.3.jar
gs_jython-0.13.0.dist-info/METADATA
gs_jython-0.13.0.dist-info/WHEEL
gs_jython-0.13.0.dist-info/top_level.txt
gs_jython-0.13.0.dist-info/RECORD
